src/rtl/rv32i_defines.v
// I type inst
`define INST_TYPE_I 7'b0010011
`define INST_ADDI   3'b000
`define INST_SLTI   3'b010
`define INST_SLTIU  3'b011
`define INST_XORI   3'b100
`define INST_ORI    3'b110
`define INST_ANDI   3'b111
`define INST_SLLI   3'b001
`define INST_SRLI    3'b101

// L type inst
`define INST_TYPE_L 7'b0000011
`define INST_LB     3'b000
`define INST_LH     3'b001
`define INST_LW     3'b010
`define INST_LBU    3'b100
`define INST_LHU    3'b101

// S type inst
`define INST_TYPE_S 7'b0100011
`define INST_SB     3'b000
`define INST_SH     3'b001
`define INST_SW     3'b010

// R and M type inst
`define INST_TYPE_R_M 7'b0110011
// R type inst
`define INST_ADD_SUB 3'b000
`define INST_SLL    3'b001
`define INST_SLT    3'b010
`define INST_SLTU   3'b011
`define INST_XOR    3'b100
`define INST_SRL     3'b101  
`define INST_OR     3'b110
`define INST_AND    3'b111
// M type inst
`define INST_MUL    3'b000
`define INST_MULH   3'b001
`define INST_MULHSU 3'b010
`define INST_MULHU  3'b011
`define INST_DIV    3'b100
`define INST_DIVU   3'b101
`define INST_REM    3'b110
`define INST_REMU   3'b111

// J type inst
`define INST_JAL    7'b1101111
`define INST_JALR   7'b1100111

`define INST_LUI    7'b0110111
`define INST_AUIPC  7'b0010111
`define INST_NOP    32'h00000001
`define INST_NOP_OP 7'b0000001
`define INST_MRET   32'h30200073
`define INST_RET    32'h00008067

`define INST_FENCE  7'b0001111
`define INST_ECALL  32'h73
`define INST_EBREAK 32'h00100073

// J type inst
`define INST_TYPE_B 7'b1100011
`define INST_BEQ    3'b000
`define INST_BNE    3'b001
`define INST_BLT    3'b100
`define INST_BGE    3'b101
`define INST_BLTU   3'b110
`define INST_BGEU   3'b111

// CSR inst
`define INST_CSR    7'b1110011
`define INST_CSRRW  3'b001
`define INST_CSRRS  3'b010
`define INST_CSRRC  3'b011
`define INST_CSRRWI 3'b101
`define INST_CSRRSI 3'b110
`define INST_CSRRCI 3'b111

src/rtl/core/pc.v
module pc(
    input wire clk,
    input wire rst,
    //from ex->ctrl->this
    input wire jump_flag_i,
    input wire[`InstAddrBus] jump_addr_i,
    //from ctrl
    input wire [`Hold_Flag_Bus] hold_flag_i,
    //to id, risc interconncet bus
    output reg [`InstAddrBus] pc_o,
    //from jtag
    input wire jtag_reset_flag_i
);
always@(posedge clk) begin
    if(rst|jtag_reset_flag_i) begin
        pc_o <= `ZeroWord;
    end else if(jump_flag_i) begin
        pc_o <= jump_addr_i;
    end else if(hold_flag_i > `Hold_Pc) begin
        pc_o <= pc_o;
    end else begin
        pc_o <= pc_o + 32'd4;
    end
end

endmodule

src/rtl/tb/quick_sim_pc.v
`timescale 1ns/1ns
`include "../core/rv32i_defines.v"
`include "../core/pc.v"
module quick_sim_pc;
reg clk,rst,jump_flag_i,jtag_reset_flag_i;
reg [`InstAddrBus] jump_addr_i;
wire [`InstAddrBus] pc_o;
reg [`Hold_Flag_Bus] hold_flag_i;
localparam JMPADDR = 32'hfefeabab; 
pc u_pc(
    .clk               (clk               ),
    .rst               (rst               ),
    .jump_flag_i       (jump_flag_i       ),
    .jump_addr_i       (jump_addr_i       ),
    .hold_flag_i       (hold_flag_i       ),
    .pc_o              (pc_o              ),
    .jtag_reset_flag_i (jtag_reset_flag_i )
);

initial begin
  clk = 0;
  repeat(100) #5 clk = ~clk;
end

initial begin
{rst,jtag_reset_flag_i} <= 2'b11;
jump_flag_i <= 0;
hold_flag_i <= `Hold_None;
#10 {rst,jtag_reset_flag_i} <= 2'b10;
#10 {rst,jtag_reset_flag_i} <= 2'b01;
#10 {rst,jtag_reset_flag_i} <= 2'b00;
#100
    jump_flag_i <= 1;
    jump_addr_i <= JMPADDR;
    @(posedge clk);
    jump_flag_i <= 0;

#100 jump_flag_i <= 0;
#100 
    hold_flag_i <= `Hold_Id;
#20
    hold_flag_i <= `Hold_None;
end

initial begin
    $dumpfile("quick_sim_pc.vcd");
    $dumpvars(0, quick_sim_pc);
end

endmodule

src/rtl/tb/quick_sim_pc.vcd
$date
	Tue Sep 24 13:26:57 2024
$end
$version
	Icarus Verilog
$end
$timescale
	1ns
$end
$scope module quick_sim_pc $end
$var wire 32 ! pc_o [31:0] $end
$var reg 1 " clk $end
$var reg 3 # hold_flag_i [2:0] $end
$var reg 1 $ jtag_reset_flag_i $end
$var reg 32 % jump_addr_i [31:0] $end
$var reg 1 & jump_flag_i $end
$var reg 1 ' rst $end
$scope module u_pc $end
$var wire 1 " clk $end
$var wire 3 ( hold_flag_i [2:0] $end
$var wire 1 $ jtag_reset_flag_i $end
$var wire 32 ) jump_addr_i [31:0] $end
$var wire 1 & jump_flag_i $end
$var wire 1 ' rst $end
$var reg 32 * pc_o [31:0] $end
$upscope $end
$upscope $end
$enddefinitions $end
#0
$dumpvars
bx *
bx )
b0 (
1'
0&
bx %
1$
b0 #
0"
bx !
$end
#5
b0 !
b0 *
1"
#10
0$
0"
#15
1"
#20
0'
1$
0"
#25
1"
#30
0$
0"
#35
b100 !
b100 *
1"
#40
0"
#45
b1000 !
b1000 *
1"
#50
0"
#55
b1100 !
b1100 *
1"
#60
0"
#65
b10000 !
b10000 *
1"
#70
0"
#75
b10100 !
b10100 *
1"
#80
0"
#85
b11000 !
b11000 *
1"
#90
0"
#95
b11100 !
b11100 *
1"
#100
0"
#105
b100000 !
b100000 *
1"
#110
0"
#115
b100100 !
b100100 *
1"
#120
0"
#125
b101000 !
b101000 *
1"
#130
b11111110111111101010101110101011 %
b11111110111111101010101110101011 )
1&
0"
#135
b11111110111111101010101110101011 !
b11111110111111101010101110101011 *
0&
1"
#140
0"
#145
b11111110111111101010101110101111 !
b11111110111111101010101110101111 *
1"
#150
0"
#155
b11111110111111101010101110110011 !
b11111110111111101010101110110011 *
1"
#160
0"
#165
b11111110111111101010101110110111 !
b11111110111111101010101110110111 *
1"
#170
0"
#175
b11111110111111101010101110111011 !
b11111110111111101010101110111011 *
1"
#180
0"
#185
b11111110111111101010101110111111 !
b11111110111111101010101110111111 *
1"
#190
0"
#195
b11111110111111101010101111000011 !
b11111110111111101010101111000011 *
1"
#200
0"
#205
b11111110111111101010101111000111 !
b11111110111111101010101111000111 *
1"
#210
0"
#215
b11111110111111101010101111001011 !
b11111110111111101010101111001011 *
1"
#220
0"
#225
b11111110111111101010101111001111 !
b11111110111111101010101111001111 *
1"
#230
0"
#235
b11111110111111101010101111010011 !
b11111110111111101010101111010011 *
1"
#240
0"
#245
b11111110111111101010101111010111 !
b11111110111111101010101111010111 *
1"
#250
0"
#255
b11111110111111101010101111011011 !
b11111110111111101010101111011011 *
1"
#260
0"
#265
b11111110111111101010101111011111 !
b11111110111111101010101111011111 *
1"
#270
0"
#275
b11111110111111101010101111100011 !
b11111110111111101010101111100011 *
1"
#280
0"
#285
b11111110111111101010101111100111 !
b11111110111111101010101111100111 *
1"
#290
0"
#295
b11111110111111101010101111101011 !
b11111110111111101010101111101011 *
1"
#300
0"
#305
b11111110111111101010101111101111 !
b11111110111111101010101111101111 *
1"
#310
0"
#315
b11111110111111101010101111110011 !
b11111110111111101010101111110011 *
1"
#320
0"
#325
b11111110111111101010101111110111 !
b11111110111111101010101111110111 *
1"
#330
0"
#335
b11111110111111101010101111111011 !
b11111110111111101010101111111011 *
b11 #
b11 (
1"
#340
0"
#345
1"
#350
0"
#355
b0 #
b0 (
1"
#360
0"
#365
b11111110111111101010101111111111 !
b11111110111111101010101111111111 *
1"
#370
0"
#375
b11111110111111101010110000000011 !
b11111110111111101010110000000011 *
1"
#380
0"
#385
b11111110111111101010110000000111 !
b11111110111111101010110000000111 *
1"
#390
0"
#395
b11111110111111101010110000001011 !
b11111110111111101010110000001011 *
1"
#400
0"
#405
b11111110111111101010110000001111 !
b11111110111111101010110000001111 *
1"
#410
0"
#415
b11111110111111101010110000010011 !
b11111110111111101010110000010011 *
1"
#420
0"
#425
b11111110111111101010110000010111 !
b11111110111111101010110000010111 *
1"
#430
0"
#435
b11111110111111101010110000011011 !
b11111110111111101010110000011011 *
1"
#440
0"
#445
b11111110111111101010110000011111 !
b11111110111111101010110000011111 *
1"
#450
0"
#455
b11111110111111101010110000100011 !
b11111110111111101010110000100011 *
1"
#460
0"
#465
b11111110111111101010110000100111 !
b11111110111111101010110000100111 *
1"
#470
0"
#475
b11111110111111101010110000101011 !
b11111110111111101010110000101011 *
1"
#480
0"
#485
b11111110111111101010110000101111 !
b11111110111111101010110000101111 *
1"
#490
0"
#495
b11111110111111101010110000110011 !
b11111110111111101010110000110011 *
1"
